README.md
setup.py
MentoDB/__init__.py
MentoDB/cli.py
MentoDB/connection.py
MentoDB/models.py
MentoDB/plugins.py
MentoDB/tests.py
MentoDB/utils.py
MentoDB.egg-info/PKG-INFO
MentoDB.egg-info/SOURCES.txt
MentoDB.egg-info/dependency_links.txt
MentoDB.egg-info/entry_points.txt
MentoDB.egg-info/requires.txt
MentoDB.egg-info/top_level.txt