Metadata-Version: 2.1
Name: MentoDB
Version: 2.1.0
Summary: Sqlite3 based powerful database project.
Home-page: https://github.com/fswair/MentoDB
Author: Mert Sırakaya
Author-email: usirakaya@ogr.iu.edu.tr
License: GPLv3+
Keywords: MentoDB,SQL,ORM
Classifier: Development Status :: 5 - Production/Stable
Classifier: License :: OSI Approved :: GNU General Public License v3 or later (GPLv3+)
Classifier: Programming Language :: Python :: 3
Requires-Python: >=3.10
